LICENSE
MANIFEST.in
README.md
setup.py
block_ip/__init__.py
block_ip/admin.py
block_ip/middleware.py
block_ip/models.py
django_block_ip.egg-info/PKG-INFO
django_block_ip.egg-info/SOURCES.txt
django_block_ip.egg-info/dependency_links.txt
django_block_ip.egg-info/requires.txt
django_block_ip.egg-info/top_level.txt