Metadata-Version: 1.1
Name: django-block-ip
Version: 0.2.0
Summary: Simple IP and IP-range blocking for Django
Home-page: http://github.com/philipn/django-block-ip
Author: Philip Neustrom
Author-email: philipn@gmail.com
License: BSD
Platform: UNKNOWN
Classifier: Development Status :: 5 - Production/Stable
Classifier: Environment :: Web Environment
Classifier: Framework :: Django
Classifier: Intended Audience :: Developers
Classifier: License :: OSI Approved :: BSD License
Classifier: Operating System :: OS Independent
Classifier: Programming Language :: Python
Classifier: Topic :: Internet :: WWW/HTTP
